atc_ble/__init__.py
atc_ble/parser.py
atc_ble/py.typed
atc_ble-0.1.0.dist-info/LICENSE
atc_ble-0.1.0.dist-info/WHEEL
atc_ble-0.1.0.dist-info/METADATA
atc_ble-0.1.0.dist-info/RECORD
